README.md
padaos.py
setup.py
padaos.egg-info/PKG-INFO
padaos.egg-info/SOURCES.txt
padaos.egg-info/dependency_links.txt
padaos.egg-info/top_level.txt
padaos.egg-info/zip-safe