Metadata-Version: 1.0
Name: padaos
Version: 0.1.0
Summary: A rigid, lightweight, dead-simple intent parser
Home-page: http://github.com/MatthewScholefield/padaos
Author: Matthew Scholefield
Author-email: matthew331199@gmail.com
License: MIT
Platform: UNKNOWN
